{"label_info": {"image": {"file_name": "livestock_cow_keypoints_000754.jpg", "width": 381, "height": 302, "farm_name": "None", "farm_env": "None", "time": "None"}, "annotations": [{"bbox": [0, 0, 381, 302], "keypoints": [357, 148, 2, 312, 118, 2, 274, 76, 2, 237, 199, 1, 213, 220, 1, 188, 271, 1, 255, 210, 1, 227, 224, 1, 205, 269, 1, 89, 18, 2, 61, 128, 1, 35, 168, 1, 18, 235, 2, 25, 102, 1, 13, 151, 1, 7, 209, 1, 62, 14, 2], "category_id": 1}], "categories": [{"supercategory": "livestock_cow", "id": 1, "name": "cattle", "keypoints_name": ["fore_head", "neck", "fore_spine", "fore_right_shoulder", "fore_right_knee", "fore_right_foot", "fore_left_shoulder", "fore_left_knee", "fore_left_foot", "rear_spine", "rear_right_shoulder", "rear_right_knee", "rear_right_foot", "rear_left_shoulder", "rear_left_knee", "rear_left_foot", "hip"], "skeleton": [[1, 2], [2, 3], [3, 4], [3, 7], [3, 10], [4, 5], [5, 6], [7, 8], [8, 9], [10, 11], [10, 14], [11, 12], [12, 13], [14, 15], [15, 16], [10, 17]]}, {"supercategory": "livestock_cow", "id": 2, "name": "nuptial", "keypoints_name": ["fore_head", "neck", "fore_spine", "fore_right_shoulder", "fore_right_knee", "fore_right_foot", "fore_left_shoulder", "fore_left_knee", "fore_left_foot", "rear_spine", "rear_right_shoulder", "rear_right_knee", "rear_right_foot", "rear_left_shoulder", "rear_left_knee", "rear_left_foot", "hip"], "skeleton": [[1, 2], [2, 3], [3, 4], [3, 7], [3, 10], [4, 5], [5, 6], [7, 8], [8, 9], [10, 11], [10, 14], [11, 12], [12, 13], [14, 15], [15, 16], [10, 17]]}, {"supercategory": "livestock_cow", "id": 3, "name": "calf", "keypoints_name": ["fore_head", "neck", "fore_spine", "fore_right_shoulder", "fore_right_knee", "fore_right_foot", "fore_left_shoulder", "fore_left_knee", "fore_left_foot", "rear_spine", "rear_right_shoulder", "rear_right_knee", "rear_right_foot", "rear_left_shoulder", "rear_left_knee", "rear_left_foot", "hip"], "skeleton": [[1, 2], [2, 3], [3, 4], [3, 7], [3, 10], [4, 5], [5, 6], [7, 8], [8, 9], [10, 11], [10, 14], [11, 12], [12, 13], [14, 15], [15, 16], [10, 17]]}]}}