{"label_info": {"image": {"file_name": "livestock_cow_keypoints_003034.jpg", "width": 152, "height": 193, "farm_name": "chuncheon", "farm_env": "open", "time": "daytime"}, "annotations": [{"bbox": [0, 0, 152, 193], "keypoints": [21, 9, 2, 37, 23, 2, 56, 31, 2, 54, 84, 1, 45, 118, 2, 33, 150, 2, 37, 71, 2, 23, 93, 2, 7, 106, 1, 111, 43, 2, 112, 102, 1, 104, 147, 1, 93, 180, 1, 104, 101, 2, 99, 146, 2, 88, 181, 2, 136, 61, 2], "category_id": 3}], "categories": [{"supercategory": "livestock_cow", "id": 1, "name": "cattle", "keypoints_name": ["fore_head", "neck", "fore_spine", "fore_right_shoulder", "fore_right_knee", "fore_right_foot", "fore_left_shoulder", "fore_left_knee", "fore_left_foot", "rear_spine", "rear_right_shoulder", "rear_right_knee", "rear_right_foot", "rear_left_shoulder", "rear_left_knee", "rear_left_foot", "hip"], "skeleton": [[1, 2], [2, 3], [3, 4], [3, 7], [3, 10], [4, 5], [5, 6], [7, 8], [8, 9], [10, 11], [10, 14], [11, 12], [12, 13], [14, 15], [15, 16], [10, 17]]}, {"supercategory": "livestock_cow", "id": 2, "name": "nuptial", "keypoints_name": ["fore_head", "neck", "fore_spine", "fore_right_shoulder", "fore_right_knee", "fore_right_foot", "fore_left_shoulder", "fore_left_knee", "fore_left_foot", "rear_spine", "rear_right_shoulder", "rear_right_knee", "rear_right_foot", "rear_left_shoulder", "rear_left_knee", "rear_left_foot", "hip"], "skeleton": [[1, 2], [2, 3], [3, 4], [3, 7], [3, 10], [4, 5], [5, 6], [7, 8], [8, 9], [10, 11], [10, 14], [11, 12], [12, 13], [14, 15], [15, 16], [10, 17]]}, {"supercategory": "livestock_cow", "id": 3, "name": "calf", "keypoints_name": ["fore_head", "neck", "fore_spine", "fore_right_shoulder", "fore_right_knee", "fore_right_foot", "fore_left_shoulder", "fore_left_knee", "fore_left_foot", "rear_spine", "rear_right_shoulder", "rear_right_knee", "rear_right_foot", "rear_left_shoulder", "rear_left_knee", "rear_left_foot", "hip"], "skeleton": [[1, 2], [2, 3], [3, 4], [3, 7], [3, 10], [4, 5], [5, 6], [7, 8], [8, 9], [10, 11], [10, 14], [11, 12], [12, 13], [14, 15], [15, 16], [10, 17]]}]}}