{"label_info": {"image": {"file_name": "livestock_cow_keypoints_008201.jpg", "width": 705, "height": 442, "farm_name": "yangpyeong", "farm_env": "open", "time": "daytime"}, "annotations": [{"bbox": [0, 0, 705, 442], "keypoints": [115, 31, 2, 157, 51, 2, 302, 33, 2, 272, 237, 1, 263, 272, 1, 218, 361, 2, 293, 252, 2, 289, 319, 2, 254, 415, 2, 633, 123, 2, 617, 293, 1, 600, 333, 1, 576, 399, 1, 581, 321, 2, 570, 379, 2, 540, 425, 1, 686, 158, 2], "category_id": 1}], "categories": [{"supercategory": "livestock_cow", "id": 1, "name": "cattle", "keypoints_name": ["fore_head", "neck", "fore_spine", "fore_right_shoulder", "fore_right_knee", "fore_right_foot", "fore_left_shoulder", "fore_left_knee", "fore_left_foot", "rear_spine", "rear_right_shoulder", "rear_right_knee", "rear_right_foot", "rear_left_shoulder", "rear_left_knee", "rear_left_foot", "hip"], "skeleton": [[1, 2], [2, 3], [3, 4], [3, 7], [3, 10], [4, 5], [5, 6], [7, 8], [8, 9], [10, 11], [10, 14], [11, 12], [12, 13], [14, 15], [15, 16], [10, 17]]}, {"supercategory": "livestock_cow", "id": 2, "name": "nuptial", "keypoints_name": ["fore_head", "neck", "fore_spine", "fore_right_shoulder", "fore_right_knee", "fore_right_foot", "fore_left_shoulder", "fore_left_knee", "fore_left_foot", "rear_spine", "rear_right_shoulder", "rear_right_knee", "rear_right_foot", "rear_left_shoulder", "rear_left_knee", "rear_left_foot", "hip"], "skeleton": [[1, 2], [2, 3], [3, 4], [3, 7], [3, 10], [4, 5], [5, 6], [7, 8], [8, 9], [10, 11], [10, 14], [11, 12], [12, 13], [14, 15], [15, 16], [10, 17]]}, {"supercategory": "livestock_cow", "id": 3, "name": "calf", "keypoints_name": ["fore_head", "neck", "fore_spine", "fore_right_shoulder", "fore_right_knee", "fore_right_foot", "fore_left_shoulder", "fore_left_knee", "fore_left_foot", "rear_spine", "rear_right_shoulder", "rear_right_knee", "rear_right_foot", "rear_left_shoulder", "rear_left_knee", "rear_left_foot", "hip"], "skeleton": [[1, 2], [2, 3], [3, 4], [3, 7], [3, 10], [4, 5], [5, 6], [7, 8], [8, 9], [10, 11], [10, 14], [11, 12], [12, 13], [14, 15], [15, 16], [10, 17]]}]}}