{"label_info": {"image": {"file_name": "livestock_cow_keypoints_005039.jpg", "width": 368, "height": 283, "farm_name": "yangpyeong", "farm_env": "open", "time": "daytime"}, "annotations": [{"bbox": [0, 0, 368, 283], "keypoints": [18, 124, 2, 64, 97, 2, 178, 41, 2, 163, 181, 1, 171, 220, 2, 161, 281, 1, 207, 181, 2, 202, 243, 2, 207, 277, 1, 306, 15, 2, 332, 145, 1, 318, 189, 1, 298, 232, 1, 333, 134, 2, 308, 187, 2, 283, 252, 2, 327, 6, 1], "category_id": 1}], "categories": [{"supercategory": "livestock_cow", "id": 1, "name": "cattle", "keypoints_name": ["fore_head", "neck", "fore_spine", "fore_right_shoulder", "fore_right_knee", "fore_right_foot", "fore_left_shoulder", "fore_left_knee", "fore_left_foot", "rear_spine", "rear_right_shoulder", "rear_right_knee", "rear_right_foot", "rear_left_shoulder", "rear_left_knee", "rear_left_foot", "hip"], "skeleton": [[1, 2], [2, 3], [3, 4], [3, 7], [3, 10], [4, 5], [5, 6], [7, 8], [8, 9], [10, 11], [10, 14], [11, 12], [12, 13], [14, 15], [15, 16], [10, 17]]}, {"supercategory": "livestock_cow", "id": 2, "name": "nuptial", "keypoints_name": ["fore_head", "neck", "fore_spine", "fore_right_shoulder", "fore_right_knee", "fore_right_foot", "fore_left_shoulder", "fore_left_knee", "fore_left_foot", "rear_spine", "rear_right_shoulder", "rear_right_knee", "rear_right_foot", "rear_left_shoulder", "rear_left_knee", "rear_left_foot", "hip"], "skeleton": [[1, 2], [2, 3], [3, 4], [3, 7], [3, 10], [4, 5], [5, 6], [7, 8], [8, 9], [10, 11], [10, 14], [11, 12], [12, 13], [14, 15], [15, 16], [10, 17]]}, {"supercategory": "livestock_cow", "id": 3, "name": "calf", "keypoints_name": ["fore_head", "neck", "fore_spine", "fore_right_shoulder", "fore_right_knee", "fore_right_foot", "fore_left_shoulder", "fore_left_knee", "fore_left_foot", "rear_spine", "rear_right_shoulder", "rear_right_knee", "rear_right_foot", "rear_left_shoulder", "rear_left_knee", "rear_left_foot", "hip"], "skeleton": [[1, 2], [2, 3], [3, 4], [3, 7], [3, 10], [4, 5], [5, 6], [7, 8], [8, 9], [10, 11], [10, 14], [11, 12], [12, 13], [14, 15], [15, 16], [10, 17]]}]}}