{"label_info": {"image": {"file_name": "livestock_cow_keypoints_003782.jpg", "width": 381, "height": 501, "farm_name": "yangpyeong", "farm_env": "open", "time": "daytime"}, "annotations": [{"bbox": [0, 0, 381, 501], "keypoints": [88, 336, 2, 52, 291, 2, 41, 234, 2, 209, 355, 1, 235, 392, 1, 258, 428, 1, 174, 380, 1, 198, 421, 2, 232, 458, 2, 198, 21, 2, 280, 130, 2, 329, 161, 2, 363, 222, 2, 273, 180, 2, 279, 214, 2, 284, 263, 2, 217, 11, 1], "category_id": 1}], "categories": [{"supercategory": "livestock_cow", "id": 1, "name": "cattle", "keypoints_name": ["fore_head", "neck", "fore_spine", "fore_right_shoulder", "fore_right_knee", "fore_right_foot", "fore_left_shoulder", "fore_left_knee", "fore_left_foot", "rear_spine", "rear_right_shoulder", "rear_right_knee", "rear_right_foot", "rear_left_shoulder", "rear_left_knee", "rear_left_foot", "hip"], "skeleton": [[1, 2], [2, 3], [3, 4], [3, 7], [3, 10], [4, 5], [5, 6], [7, 8], [8, 9], [10, 11], [10, 14], [11, 12], [12, 13], [14, 15], [15, 16], [10, 17]]}, {"supercategory": "livestock_cow", "id": 2, "name": "nuptial", "keypoints_name": ["fore_head", "neck", "fore_spine", "fore_right_shoulder", "fore_right_knee", "fore_right_foot", "fore_left_shoulder", "fore_left_knee", "fore_left_foot", "rear_spine", "rear_right_shoulder", "rear_right_knee", "rear_right_foot", "rear_left_shoulder", "rear_left_knee", "rear_left_foot", "hip"], "skeleton": [[1, 2], [2, 3], [3, 4], [3, 7], [3, 10], [4, 5], [5, 6], [7, 8], [8, 9], [10, 11], [10, 14], [11, 12], [12, 13], [14, 15], [15, 16], [10, 17]]}, {"supercategory": "livestock_cow", "id": 3, "name": "calf", "keypoints_name": ["fore_head", "neck", "fore_spine", "fore_right_shoulder", "fore_right_knee", "fore_right_foot", "fore_left_shoulder", "fore_left_knee", "fore_left_foot", "rear_spine", "rear_right_shoulder", "rear_right_knee", "rear_right_foot", "rear_left_shoulder", "rear_left_knee", "rear_left_foot", "hip"], "skeleton": [[1, 2], [2, 3], [3, 4], [3, 7], [3, 10], [4, 5], [5, 6], [7, 8], [8, 9], [10, 11], [10, 14], [11, 12], [12, 13], [14, 15], [15, 16], [10, 17]]}]}}